evolvepy/__init__.py
evolvepy/configurable.py
evolvepy/evolver.py
evolvepy/callbacks/__init__.py
evolvepy/callbacks/callback.py
evolvepy/callbacks/dynamic_mutation.py
evolvepy/callbacks/incremental_evolution.py
evolvepy/callbacks/logger.py
evolvepy/evaluator/__init__.py
evolvepy/evaluator/aggregator.py
evolvepy/evaluator/cache.py
evolvepy/evaluator/evaluator.py
evolvepy/evaluator/function_evaluator.py
evolvepy/evaluator/multiple.py
evolvepy/evaluator/process_evaluator.py
evolvepy/generator/__init__.py
evolvepy/generator/basic_layers.py
evolvepy/generator/combine.py
evolvepy/generator/context.py
evolvepy/generator/descriptor.py
evolvepy/generator/firstgen.py
evolvepy/generator/generator.py
evolvepy/generator/layer.py
evolvepy/generator/thread_pool.py
evolvepy/generator/crossover/__init__.py
evolvepy/generator/crossover/crossover.py
evolvepy/generator/mutation/__init__.py
evolvepy/generator/mutation/binary_mutation.py
evolvepy/generator/mutation/mutation.py
evolvepy/generator/mutation/numeric_mutation.py
evolvepy/generator/selection/__init__.py
evolvepy/generator/selection/selection.py
evolvepy/integrations/__init__.py
evolvepy/integrations/gym/__init__.py
evolvepy/integrations/gym/gym.py
evolvepy/integrations/nvtx/__init__.py
evolvepy/integrations/nvtx/annotate_se.py
evolvepy/integrations/nvtx/colors.py
evolvepy/integrations/nvtx/mock.py
evolvepy/integrations/ray/__init__.py
evolvepy/integrations/ray/distributed_evaluator.py
evolvepy/integrations/tf_keras/__init__.py
evolvepy/integrations/tf_keras/tf_keras.py
evolvepy/integrations/unity_gym/__init__.py
evolvepy/integrations/unity_gym/unity.py
evolvepy/integrations/wandb/__init__.py
evolvepy/integrations/wandb/wandb.py
evolvepy-2.0.0.dist-info/.gitignore
evolvepy-2.0.0.dist-info/LICENSE
evolvepy-2.0.0.dist-info/METADATA
evolvepy-2.0.0.dist-info/WHEEL
evolvepy-2.0.0.dist-info/top_level.txt
evolvepy-2.0.0.dist-info/RECORD
