Metadata-Version: 2.1
Name: evolvepy
Version: 2.0.0
Summary: EvolvePy is a Python module created to allow the easy creation and execution of evolutionary algorithms.
Home-page: https://github.com/EltonCN/evolvepy
Author: EltonCN, João Bonucci, Thiago Lacerda
Author-email: elton.nascimento@students.ic.unicamp.br, j218733@dac.unicamp.br, t244712@dac.unicamp.br
License: MIT
Project-URL: Bug Tracker, https://github.com/EltonCN/evolvepy/issues
Project-URL: Documentation, https://eltoncn.github.io/evolvepy
Classifier: License :: OSI Approved :: MIT License
Classifier: Programming Language :: Python :: 3
Classifier: Operating System :: OS Independent
Classifier: Topic :: Scientific/Engineering
Classifier: Topic :: Scientific/Engineering :: Artificial Intelligence
Classifier: Intended Audience :: Science/Research
Requires-Python: >=3.7
License-File: LICENSE
Requires-Dist: numpy (>=1.20)
Requires-Dist: numba
Provides-Extra: all_integrations
Requires-Dist: mlagents (>=0.27.0) ; extra == 'all_integrations'
Requires-Dist: gym-unity ; extra == 'all_integrations'
Requires-Dist: gym ; extra == 'all_integrations'
Requires-Dist: wandb ; extra == 'all_integrations'
Requires-Dist: tensorflow ; extra == 'all_integrations'
Provides-Extra: doc_generation
Requires-Dist: sphinx ; extra == 'doc_generation'
Requires-Dist: m2r2 ; extra == 'doc_generation'
Requires-Dist: sphinx-rtd-theme ; extra == 'doc_generation'
Provides-Extra: gym
Requires-Dist: gym (<=0.21.0) ; extra == 'gym'
Provides-Extra: ray
Requires-Dist: ray ; extra == 'ray'
Provides-Extra: tensorflow
Requires-Dist: tensorflow ; extra == 'tensorflow'
Provides-Extra: unity
Requires-Dist: mlagents (>=0.27.0) ; extra == 'unity'
Requires-Dist: gym-unity ; extra == 'unity'
Requires-Dist: gym ; extra == 'unity'
Provides-Extra: wandb
Requires-Dist: wandb ; extra == 'wandb'
